typio/__init__.py
typio/__main__.py
typio/errors.py
typio/functions.py
typio/params.py
typio-0.1.dist-info/licenses/AUTHORS.md
typio-0.1.dist-info/licenses/LICENSE
typio-0.1.dist-info/METADATA
typio-0.1.dist-info/WHEEL
typio-0.1.dist-info/top_level.txt
typio-0.1.dist-info/RECORD
