Metadata-Version: 2.4
Name: typio
Version: 0.1
Summary: Typio: Make Your Terminal Type Like a Human
Home-page: https://github.com/sepandhaghighi/typio
Download-URL: https://github.com/sepandhaghighi/typio/tarball/v0.1
Author: Sepand Haghighi
Author-email: me@sepand.tech
License: MIT
Project-URL: Source, https://github.com/sepandhaghighi/typio
Keywords: terminal cli typing typewriter typing-effect console stdout ux
Classifier: Development Status :: 3 - Alpha
Classifier: Natural Language :: English
Classifier: License :: OSI Approved :: MIT License
Classifier: Operating System :: OS Independent
Classifier: Programming Language :: Python :: 3.8
Classifier: Programming Language :: Python :: 3.9
Classifier: Programming Language :: Python :: 3.10
Classifier: Programming Language :: Python :: 3.11
Classifier: Programming Language :: Python :: 3.12
Classifier: Programming Language :: Python :: 3.13
Classifier: Programming Language :: Python :: 3.14
Classifier: Intended Audience :: Developers
Classifier: Intended Audience :: Education
Classifier: Topic :: Software Development :: Libraries
Classifier: Topic :: Software Development :: User Interfaces
Classifier: Topic :: Software Development :: Libraries :: Python Modules
Classifier: Topic :: Utilities
Classifier: Topic :: Terminals
Requires-Python: >=3.8
License-File: LICENSE
License-File: AUTHORS.md
Dynamic: author
Dynamic: author-email
Dynamic: classifier
Dynamic: description
Dynamic: description-content-type
Dynamic: download-url
Dynamic: home-page
Dynamic: keywords
Dynamic: license
Dynamic: license-file
Dynamic: project-url
Dynamic: requires-python
Dynamic: summary
